{"level1" : [
    "XXXXXXXXXXXXX",
    "XX         XX",
    "XX    B    XX",
    "XX S    @  XX",
    "XX S  B    XX",
    "XX         XX",
    "XXXXXXXXXXXXX"
],

"level2" : [
    "XXXXXXXXXXXXX",
    "XXXXXXX@XXXXX",
    "XXXXXXXBS  XX",
    "XX    B    XX",
    "XX    S BS XX",
    "XX         XX",
    "XXXXXXXXXXXXX"
],

"level3" : [
    "XXXXXXXXXXXXX",
    "XXXXXSXXXXXXX",
    "XXXXXB B  SXX",
    "XXXS B@XXXXXX",
    "XXXXXXBXXXXXX",
    "XXXXXXSXXXXXX",
    "XXXXXXXXXXXXX"
],

"level4" : [
    "XXXXXXXXXXXXX",
    "XXXXXXXXXXXXX",
    "XXXXXXXXXXXXX",
    "X X   XXXXXXX",
    "X@B  B XX  XX",
    "XSB      SSXX",
    "XXXXXXXXXXXXX"
],

"level5" : [
    "XXXXXXXXXXXXX",
    "XXXXXXXXXXXXX",
    "X   XXXXXXXXX",
    "X X      B  X",
    "X   X  XXB  X",
    "X  S S XX@  X",
    "XXXXXXXXXXXXX"
]}